gnss_visualizer/__init__.py
gnss_visualizer/app.py
gnss_visualizer/constants.py
gnss_visualizer/conversions.py
gnss_visualizer/main.py
gnss_visualizer/run_server.py
gnss_visualizer/ubx_stream.py
gnss_visualizer/ui_handler.py
gnss_visualizer/plots/__init__.py
gnss_visualizer/plots/cno.py
gnss_visualizer/plots/generic_plot.py
gnss_visualizer/plots/map.py
gnss_visualizer/protocols/ubx.py
gnss_visualizer/translations/en/LC_MESSAGES/messages.po
gnss_visualizer/translations/fi/LC_MESSAGES/messages.po
gnss_visualizer-0.0.7.dist-info/METADATA
gnss_visualizer-0.0.7.dist-info/WHEEL
gnss_visualizer-0.0.7.dist-info/entry_points.txt
gnss_visualizer-0.0.7.dist-info/licenses/LICENSE
gnss_visualizer-0.0.7.dist-info/RECORD
