Metadata-Version: 2.3
Name: gnss-visualizer
Version: 0.0.7
Summary: Visualize GNSS data in a web browser
Project-URL: Homepage, https://github.com/jopppis/gnss-visualizer
Project-URL: Documentation, https://github.com/jopppis/gnss-visualizer
Project-URL: Repository, https://github.com/jopppis/gnss-visualizer.git
Project-URL: Bug Tracker, https://github.com/jopppis/gnss-visualizer/issues
Project-URL: Changelog, https://github.com/jopppis/gnss-visualizer/blob/main/CHANGELOG.md
Author-email: Ville Joensuu <ville.joensuu@iki.fi>
Maintainer-email: Ville Joensuu <ville.joensuu@iki.fi>
License:                     GNU AFFERO GENERAL PUBLIC LICENSE
License-File: LICENSE
Keywords: gnss,gps,nmea
Classifier: Programming Language :: Python
Requires-Python: >=3.10
Requires-Dist: bokeh
Requires-Dist: pyproj
Requires-Dist: pyserial
Requires-Dist: pyubx2
Requires-Dist: xyzservices
